src/PySCFmerger.py
src/__init__.py
src/momtensor.py
src/poltensor.py
src/qdist.py
Anoop_A_Nair-0.0.1.dist-info/LICENSE
Anoop_A_Nair-0.0.1.dist-info/METADATA
Anoop_A_Nair-0.0.1.dist-info/WHEEL
Anoop_A_Nair-0.0.1.dist-info/top_level.txt
Anoop_A_Nair-0.0.1.dist-info/RECORD
