Metadata-Version: 2.1
Name: Anoop-A-Nair
Version: 0.0.1
Summary: A small example package
Home-page: https://github.com/pypa/sampleproject
Author: Example Author
Author-email: author@example.com
Classifier: Programming Language :: Python :: 3
Classifier: License :: OSI Approved :: MIT License
Classifier: Operating System :: OS Independent
License-File: LICENSE
